vedro_d42_validator/__init__.py
vedro_d42_validator/_d42_validator.py
vedro_d42_validator/py.typed
vedro_d42_validator-1.4.0.dist-info/licenses/LICENSE
vedro_d42_validator-1.4.0.dist-info/METADATA
vedro_d42_validator-1.4.0.dist-info/WHEEL
vedro_d42_validator-1.4.0.dist-info/top_level.txt
vedro_d42_validator-1.4.0.dist-info/RECORD
